pixivpy3/__init__.py
pixivpy3/aapi.py
pixivpy3/api.py
pixivpy3/bapi.py
pixivpy3/papi.py
pixivpy3/utils.py
PixivPy-3.7.0.dist-info/LICENSE
PixivPy-3.7.0.dist-info/METADATA
PixivPy-3.7.0.dist-info/WHEEL
PixivPy-3.7.0.dist-info/top_level.txt
PixivPy-3.7.0.dist-info/RECORD
