Metadata-Version: 2.1
Name: PixivPy
Version: 3.7.0
Summary: Pixiv API for Python (with 6.x AppAPI supported)
Home-page: https://github.com/upbit/pixivpy
Author: upbit
Author-email: rmusique@gmail.com
License: UNKNOWN
Download-URL: https://github.com/upbit/pixivpy/releases
Keywords: pixiv,api,pixivpy
Platform: UNKNOWN
Classifier: Programming Language :: Python :: 2
Classifier: Programming Language :: Python :: 3
Classifier: Operating System :: OS Independent
Requires-Dist: requests (>=2.0)
Requires-Dist: requests-toolbelt (>=0.9.1)
Requires-Dist: cloudscraper (<1.2.50,>=1.0)
